CreateWorld/CreateWorld.cpython-311-aarch64-linux-gnu.so
CreateWorld/__init__.py
CreateWorld-0.2.0.dist-info/METADATA
CreateWorld-0.2.0.dist-info/WHEEL
CreateWorld-0.2.0.dist-info/top_level.txt
CreateWorld-0.2.0.dist-info/RECORD
